posggym_agents/__init__.py
posggym_agents/config.py
posggym_agents/error.py
posggym_agents/logger.py
posggym_agents/policy.py
posggym_agents/py.typed
posggym_agents/agents/__init__.py
posggym_agents/agents/random_policies.py
posggym_agents/agents/registration.py
posggym_agents/agents/utils.py
posggym_agents/agents/driving_14x14roundabout_n2_v0/__init__.py
posggym_agents/agents/driving_7x7roundabout_n2_v0/__init__.py
posggym_agents/agents/lbf/__init__.py
posggym_agents/agents/lbf/heuristic.py
posggym_agents/agents/predatorprey_10x10_P2_p3_s2_coop_v0/__init__.py
posggym_agents/agents/predatorprey_10x10_P3_p3_s2_coop_v0/__init__.py
posggym_agents/agents/predatorprey_10x10_P4_p3_s3_coop_v0/__init__.py
posggym_agents/agents/pursuitevasion/__init__.py
posggym_agents/agents/pursuitevasion/shortest_path.py
posggym_agents/agents/pursuitevasion_16x16_v0/__init__.py
posggym_agents/agents/pursuitevasion_8x8_v0/__init__.py
posggym_agents/evaluation/__init__.py
posggym_agents/evaluation/exp.py
posggym_agents/evaluation/pairwise.py
posggym_agents/evaluation/render.py
posggym_agents/evaluation/runner.py
posggym_agents/evaluation/stats.py
posggym_agents/evaluation/writer.py
posggym_agents/rllib/__init__.py
posggym_agents/rllib/policy.py
posggym_agents/rllib/preprocessors.py
posggym_agents/rllib/pbt/__init__.py
posggym_agents/rllib/pbt/interaction_graph.py
posggym_agents/rllib/pbt/klr.py
posggym_agents/rllib/pbt/sp.py
posggym_agents/rllib/pbt/utils.py
posggym_agents/rllib/train/__init__.py
posggym_agents/rllib/train/algorithm.py
posggym_agents/rllib/train/algorithm_config.py
posggym_agents/rllib/train/export_lib.py
posggym_agents/rllib/train/import_lib.py
posggym_agents/rllib/train/klr.py
posggym_agents/rllib/train/policy_mapping.py
posggym_agents/rllib/train/sp.py
posggym_agents/rllib/train/train.py
posggym_agents/rllib/train/utils.py
posggym_agents/utils/__init__.py
posggym_agents/utils/download.py
posggym_agents-0.3.1.dist-info/LICENSE
posggym_agents-0.3.1.dist-info/METADATA
posggym_agents-0.3.1.dist-info/WHEEL
posggym_agents-0.3.1.dist-info/top_level.txt
posggym_agents-0.3.1.dist-info/RECORD
