Metadata-Version: 2.1
Name: posggym-agents
Version: 0.3.1
Summary: A collection of agents and agent training code for posggym.
Author-email: Jonathon Schwartz <jonathon.schwartz@anu.edu.au>
License: MIT License
Project-URL: Homepage, https://github.com/Jjschwartz/posggym-agents
Project-URL: Repository, https://github.com/Jjschwartz/posggym-agents
Project-URL: Documentation, https://github.com/Jjschwartz/posggym-agents
Project-URL: Bug Report, https://github.com/Jjschwartz/posggym-agents/issues
Keywords: reinforcement learning,games,RL,AI,planning,posg
Classifier: Development Status :: 3 - Alpha
Classifier: License :: OSI Approved :: MIT License
Classifier: Programming Language :: Python :: 3
Classifier: Programming Language :: Python :: 3.8
Classifier: Programming Language :: Python :: 3.9
Classifier: Programming Language :: Python :: 3.10
Classifier: Programming Language :: Python :: 3.11
Classifier: Intended Audience :: Science/Research
Classifier: Topic :: Scientific/Engineering :: Artificial Intelligence
Requires-Python: >=3.8
License-File: LICENSE
Requires-Dist: posggym (>=0.3.1)
Requires-Dist: numpy (>1.21)
Requires-Dist: pandas (>=1.0)
Requires-Dist: prettytable (>=3.6.0)
Requires-Dist: typing-extensions (>=4.3.0)
Requires-Dist: types-requests (>=2.28)
Requires-Dist: requests (>=2.28)
Requires-Dist: clint (>=0.5.1)
Requires-Dist: torch (>=1.11.0)
Requires-Dist: ray[rllib] (>=2.3)
Provides-Extra: all
Provides-Extra: testing
Requires-Dist: pytest (>=7.2) ; extra == 'testing'
